[
  { "timestamp": "2026-01-16T08:00:00Z", "value": 72.5 },
  { "timestamp": "2026-01-16T08:05:00Z", "value": 73.2 },
  { "timestamp": "2026-01-16T08:10:00Z", "value": 74.8 },
  { "timestamp": "2026-01-16T08:15:00Z", "value": 76.3 },
  { "timestamp": "2026-01-16T08:20:00Z", "value": 78.1 },
  { "timestamp": "2026-01-16T08:25:00Z", "value": 79.5 },
  { "timestamp": "2026-01-16T08:30:00Z", "value": 81.2 },
  { "timestamp": "2026-01-16T08:35:00Z", "value": 82.7 },
  { "timestamp": "2026-01-16T08:40:00Z", "value": 84.3 },
  { "timestamp": "2026-01-16T08:45:00Z", "value": 85.8 },
  { "timestamp": "2026-01-16T08:50:00Z", "value": 87.2 },
  { "timestamp": "2026-01-16T08:55:00Z", "value": 88.5 },
  { "timestamp": "2026-01-16T09:00:00Z", "value": 87.9 },
  { "timestamp": "2026-01-16T09:05:00Z", "value": 86.4 },
  { "timestamp": "2026-01-16T09:10:00Z", "value": 85.1 },
  { "timestamp": "2026-01-16T09:15:00Z", "value": 83.7 },
  { "timestamp": "2026-01-16T09:20:00Z", "value": 82.3 },
  { "timestamp": "2026-01-16T09:25:00Z", "value": 80.8 },
  { "timestamp": "2026-01-16T09:30:00Z", "value": 79.5 },
  { "timestamp": "2026-01-16T09:35:00Z", "value": 78.2 },
  { "timestamp": "2026-01-16T09:40:00Z", "value": 77.1 },
  { "timestamp": "2026-01-16T09:45:00Z", "value": 76.3 },
  { "timestamp": "2026-01-16T09:50:00Z", "value": 75.8 },
  { "timestamp": "2026-01-16T09:55:00Z", "value": 75.2 },
  { "timestamp": "2026-01-16T10:00:00Z", "value": 74.9 }
]
